{"id":100,"transliteration":"Al-'Adiyat","verses":[{"id":1,"transliteration":"WaalAAadiyati dabhan"},{"id":2,"transliteration":"Faalmooriyati qadhan"},{"id":3,"transliteration":"Faalmugheerati subhan"},{"id":4,"transliteration":"Faatharna bihi naqAAan"},{"id":5,"transliteration":"Fawasatna bihi jamAAan"},{"id":6,"transliteration":"Inna alinsana lirabbihi lakanoodun"},{"id":7,"transliteration":"Wainnahu AAala thalika lashaheedun"},{"id":8,"transliteration":"Wainnahu lihubbi alkhayri lashadeedun"},{"id":9,"transliteration":"Afala yaAAlamu itha buAAthira ma fee alquboori"},{"id":10,"transliteration":"Wahussila ma fee alssudoori"},{"id":11,"transliteration":"Inna rabbahum bihim yawmaithin lakhabeerun"}]}
